traffic_anomaly/__init__.py
traffic_anomaly/anomaly.py
traffic_anomaly/changepoint.py
traffic_anomaly/decompose.py
traffic_anomaly/sample_data.py
traffic_anomaly/data/sample_changepoint_input.parquet
traffic_anomaly/data/sample_connectivity.parquet
traffic_anomaly/data/sample_counts.parquet
traffic_anomaly/data/sample_travel_times.parquet
traffic_anomaly-2.5.3.dist-info/licenses/LICENSE
traffic_anomaly-2.5.3.dist-info/METADATA
traffic_anomaly-2.5.3.dist-info/WHEEL
traffic_anomaly-2.5.3.dist-info/top_level.txt
traffic_anomaly-2.5.3.dist-info/RECORD
