Metadata-Version: 2.4
Name: traffic_anomaly
Version: 2.5.3
Summary: Robust decomposition, anomaly and changepoint detection on multiple time series for any SQL backend. Designed for traffic data.
Author-email: Shawn Strasser <shawn.strasser@odot.oregon.gov>
Classifier: Programming Language :: Python :: 3
Classifier: License :: OSI Approved :: MIT License
Classifier: Operating System :: OS Independent
Requires-Python: >=3.9
License-File: LICENSE
Requires-Dist: ibis-framework[duckdb]<12.0.0,>=11.0.0
Dynamic: license-file
